Metadata-Version: 2.1
Name: isitkbs
Version: 1.2.2
Summary: Detect keyboard smashing
Author: Arthur de Melo, Arthur Grandão, Douglas Alves, Gabriel Campello, Paulo Victor, Rafael Ferreira, Sidney Fernando
License: MIT License
Keywords: keyboard-smashing
License-File: LICENSE
